{
  "mode": "run_attempt",
  "input_kind": "draft_lock",
  "provenance": [
    {
      "field": "contract.delivery",
      "kind": "compatibility_import",
      "source_path": "/Users/egamikohsuke/Ekoh/projects/ato/capsuled-dev/apps/ato-desktop/capsule.toml",
      "source_field": "targets.<default_target>",
      "note": "desktop native delivery mode is recorded in contract.delivery so source-derivation and artifact-import remain distinct"
    },
    {
      "field": "contract.metadata",
      "kind": "compatibility_import",
      "source_path": "/Users/egamikohsuke/Ekoh/projects/ato/capsuled-dev/apps/ato-desktop/capsule.toml",
      "source_field": "name/version/default_target"
    },
    {
      "field": "contract.process",
      "kind": "compatibility_import",
      "source_path": "/Users/egamikohsuke/Ekoh/projects/ato/capsuled-dev/apps/ato-desktop/capsule.toml",
      "source_field": "targets.<default_target>",
      "note": "single-process compatibility project synthesized from default target"
    },
    {
      "field": "contract.workloads",
      "kind": "compatibility_import",
      "source_path": "/Users/egamikohsuke/Ekoh/projects/ato/capsuled-dev/apps/ato-desktop/capsule.toml",
      "source_field": "default_target",
      "note": "single-process project synthesized into one workload for downstream consistency"
    },
    {
      "field": "resolution.resolved_targets",
      "kind": "compatibility_import",
      "source_path": "/Users/egamikohsuke/Ekoh/projects/ato/capsuled-dev/apps/ato-desktop/capsule.toml",
      "source_field": "targets",
      "note": "manifest target definitions lifted as resolution-owned hints"
    },
    {
      "field": "resolution.target_selection",
      "kind": "compatibility_import",
      "source_path": "/Users/egamikohsuke/Ekoh/projects/ato/capsuled-dev/apps/ato-desktop/capsule.toml",
      "source_field": "default_target"
    },
    {
      "field": "resolution.runtime",
      "kind": "compatibility_import",
      "source_path": "/Users/egamikohsuke/Ekoh/projects/ato/capsuled-dev/apps/ato-desktop",
      "source_field": "resolution.target_selection",
      "note": "draft compatibility target hints promoted into an execution-ready runtime"
    },
    {
      "field": "resolution.closure",
      "kind": "deterministic_heuristic",
      "source_path": "/Users/egamikohsuke/Ekoh/projects/ato/capsuled-dev/apps/ato-desktop",
      "source_field": "project_root",
      "note": "dependency closure remained unresolved in the draft lock, so run uses metadata-only/incomplete observed lockfile state"
    },
    {
      "field": "resolution.closure",
      "kind": "importer_observation",
      "source_path": "/Users/egamikohsuke/Ekoh/projects/ato/capsuled-dev/apps/ato-desktop/Cargo.lock",
      "importer_id": "cargo",
      "evidence_kind": "lockfile",
      "source_field": "cargo",
      "note": "importer evidence observed while promoting draft closure state"
    }
  ],
  "diagnostics": [
    {
      "severity": "warning",
      "field": "contract.process",
      "message": "compatibility compiler output is a lock-shaped draft for downstream resolution and diagnostics, not an execution-usable canonical lock"
    },
    {
      "severity": "warning",
      "field": "resolution",
      "message": "legacy lock was present but did not contribute any resolution-owned data"
    }
  ],
  "selection_gate": null,
  "approval_gate": null,
  "infer": {
    "candidate_sets": [],
    "unresolved": []
  },
  "resolve": {
    "resolved_process": true,
    "resolved_runtime": true,
    "resolved_target_compatibility": true,
    "resolved_dependency_closure": true,
    "unresolved": [
      "resolution"
    ]
  }
}